cosmology/api/__init__.py
cosmology/api/_components.py
cosmology/api/_constants.py
cosmology/api/_core.py
cosmology/api/_distances.py
cosmology/api/_extras.py
cosmology/api/_namespace.py
cosmology/api/_perturbations.py
cosmology/api/_standard.py
cosmology/api/py.typed
cosmology/api/_array_api/__init__.py
cosmology/api/_array_api/array.py
cosmology/api/_array_api/dtype.py
cosmology/api/compat/__init__.py
cosmology/api/compat/_core.py
cosmology/api/compat/_standard.py
cosmology_api-0.3.2.dist-info/METADATA
cosmology_api-0.3.2.dist-info/WHEEL
cosmology_api-0.3.2.dist-info/licenses/AUTHORS.rst
cosmology_api-0.3.2.dist-info/licenses/LICENSE.txt
cosmology_api-0.3.2.dist-info/RECORD
