Metadata-Version: 2.4
Name: cosmology.api
Version: 0.3.2
Summary: Cosmology API standard
Project-URL: homepage, https://cosmology.readthedocs.org/projects/api
Project-URL: repository, https://github.com/cosmology-api/cosmology.api
Project-URL: documentation, https://cosmology.readthedocs.org/projects/api
Author-email: Nathaniel Starkman <n.starkman@mail.utoronto.ca>, Nicolas Tessore <n.tessore@ucl.ac.uk>
Maintainer-email: Nathaniel Starkman <n.starkman@mail.utoronto.ca>, Nicolas Tessore <n.tessore@ucl.ac.uk>
License: BSD 3-Clause License
License-File: AUTHORS.rst
License-File: LICENSE.txt
Keywords: API,cosmology
Classifier: Intended Audience :: Developers
Classifier: Intended Audience :: Science/Research
Classifier: License :: OSI Approved :: BSD License
Classifier: Operating System :: OS Independent
Classifier: Programming Language :: Python :: 3
Requires-Python: >=3.9
Provides-Extra: all
Provides-Extra: docs
Requires-Dist: furo; extra == 'docs'
Requires-Dist: numpydoc; extra == 'docs'
Requires-Dist: sphinx; extra == 'docs'
Requires-Dist: sphinx-copybutton; extra == 'docs'
Requires-Dist: sybil; extra == 'docs'
Requires-Dist: tomli; extra == 'docs'
Requires-Dist: typing-extensions; extra == 'docs'
Provides-Extra: test
Requires-Dist: coverage[toml]; extra == 'test'
Requires-Dist: numpy>=1.21; extra == 'test'
Requires-Dist: packaging; extra == 'test'
Requires-Dist: pytest; extra == 'test'
Requires-Dist: pytest-cov; extra == 'test'
Requires-Dist: sybil; extra == 'test'
Requires-Dist: typing-extensions; extra == 'test'
